{
  "BTN_RFI": {
    "22": {
      "raise": 0.0629,
      "fold": 0.9371
    },
    "32s": {
      "raise": 0.0618,
      "fold": 0.9382
    },
    "42s": {
      "raise": 0.1192,
      "fold": 0.8808
    },
    "52s": {
      "raise": 0.08,
      "fold": 0.92
    },
    "62s": {
      "raise": 0.1199,
      "fold": 0.8801
    },
    "72s": {
      "raise": 0.1335,
      "fold": 0.8665
    },
    "82s": {
      "raise": 0.1569,
      "fold": 0.8431
    },
    "92s": {
      "raise": 0.1466,
      "fold": 0.8534
    },
    "T2s": {
      "raise": 0.1563,
      "fold": 0.8437
    },
    "J2s": {
      "raise": 0.2887,
      "fold": 0.7113
    },
    "Q2s": {
      "raise": 0.4423,
      "fold": 0.5577
    },
    "K2s": {
      "raise": 0.5586,
      "fold": 0.4414
    },
    "A2s": {
      "raise": 0.6477,
      "fold": 0.3523
    },
    "32o": {
      "raise": 0.0295,
      "fold": 0.9705
    },
    "33": {
      "raise": 0.0856,
      "fold": 0.9144
    },
    "43s": {
      "raise": 0.0786,
      "fold": 0.9214
    },
    "53s": {
      "raise": 0.2303,
      "fold": 0.7697
    },
    "63s": {
      "raise": 0.1356,
      "fold": 0.8644
    },
    "73s": {
      "raise": 0.2151,
      "fold": 0.7849
    },
    "83s": {
      "raise": 0.2421,
      "fold": 0.7579
    },
    "93s": {
      "raise": 0.6519,
      "fold": 0.3481
    },
    "T3s": {
      "raise": 0.4659,
      "fold": 0.5341
    },
    "J3s": {
      "raise": 0.6809,
      "fold": 0.3191
    },
    "Q3s": {
      "raise": 0.8414,
      "fold": 0.1586
    },
    "K3s": {
      "raise": 0.8805,
      "fold": 0.1195
    },
    "A3s": {
      "raise": 0.912,
      "fold": 0.088
    },
    "42o": {
      "raise": 0.0274,
      "fold": 0.9726
    },
    "43o": {
      "raise": 0.0388,
      "fold": 0.9612
    },
    "44": {
      "raise": 0.2966,
      "fold": 0.7034
    },
    "54s": {
      "raise": 0.1988,
      "fold": 0.8012
    },
    "64s": {
      "raise": 0.3326,
      "fold": 0.6674
    },
    "74s": {
      "raise": 0.7469,
      "fold": 0.2531
    },
    "84s": {
      "raise": 0.5783,
      "fold": 0.4217
    },
    "94s": {
      "raise": 0.8092,
      "fold": 0.1908
    },
    "T4s": {
      "raise": 0.8614,
      "fold": 0.1386
    },
    "J4s": {
      "raise": 0.8374,
      "fold": 0.1626
    },
    "Q4s": {
      "raise": 0.8989,
      "fold": 0.1011
    },
    "K4s": {
      "raise": 0.9216,
      "fold": 0.0784
    },
    "A4s": {
      "raise": 0.9447,
      "fold": 0.0553
    },
    "52o": {
      "raise": 0.0424,
      "fold": 0.9576
    },
    "53o": {
      "raise": 0.0684,
      "fold": 0.9316
    },
    "54o": {
      "raise": 0.1014,
      "fold": 0.8986
    },
    "55": {
      "raise": 0.8772,
      "fold": 0.1228
    },
    "65s": {
      "raise": 0.8522,
      "fold": 0.1478
    },
    "75s": {
      "raise": 0.8531,
      "fold": 0.1469
    },
    "85s": {
      "raise": 0.8783,
      "fold": 0.1217
    },
    "95s": {
      "raise": 0.9043,
      "fold": 0.0957
    },
    "T5s": {
      "raise": 0.9446,
      "fold": 0.0554
    },
    "J5s": {
      "raise": 0.9312,
      "fold": 0.0688
    },
    "Q5s": {
      "raise": 0.9482,
      "fold": 0.0518
    },
    "K5s": {
      "raise": 0.9591,
      "fold": 0.0409
    },
    "A5s": {
      "raise": 0.9619,
      "fold": 0.0381
    },
    "62o": {
      "raise": 0.04,
      "fold": 0.96
    },
    "63o": {
      "raise": 0.0806,
      "fold": 0.9194
    },
    "64o": {
      "raise": 0.124,
      "fold": 0.876
    },
    "65o": {
      "raise": 0.7138,
      "fold": 0.2862
    },
    "66": {
      "raise": 0.9482,
      "fold": 0.0518
    },
    "76s": {
      "raise": 0.9349,
      "fold": 0.0651
    },
    "86s": {
      "raise": 0.9247,
      "fold": 0.0753
    },
    "96s": {
      "raise": 0.9391,
      "fold": 0.0609
    },
    "T6s": {
      "raise": 0.9541,
      "fold": 0.0459
    },
    "J6s": {
      "raise": 0.9638,
      "fold": 0.0362
    },
    "Q6s": {
      "raise": 0.9679,
      "fold": 0.0321
    },
    "K6s": {
      "raise": 0.964,
      "fold": 0.036
    },
    "A6s": {
      "raise": 0.9801,
      "fold": 0.0199
    },
    "72o": {
      "raise": 0.0517,
      "fold": 0.9483
    },
    "73o": {
      "raise": 0.0917,
      "fold": 0.9083
    },
    "74o": {
      "raise": 0.1988,
      "fold": 0.8012
    },
    "75o": {
      "raise": 0.8663,
      "fold": 0.1337
    },
    "76o": {
      "raise": 0.9244,
      "fold": 0.0756
    },
    "77": {
      "raise": 0.972,
      "fold": 0.028
    },
    "87s": {
      "raise": 0.9639,
      "fold": 0.0361
    },
    "97s": {
      "raise": 0.9715,
      "fold": 0.0285
    },
    "T7s": {
      "raise": 0.9733,
      "fold": 0.0267
    },
    "J7s": {
      "raise": 0.9715,
      "fold": 0.0285
    },
    "Q7s": {
      "raise": 0.9782,
      "fold": 0.0218
    },
    "K7s": {
      "raise": 0.9803,
      "fold": 0.0197
    },
    "A7s": {
      "raise": 0.9805,
      "fold": 0.0195
    },
    "82o": {
      "raise": 0.0424,
      "fold": 0.9576
    },
    "83o": {
      "raise": 0.0699,
      "fold": 0.9301
    },
    "84o": {
      "raise": 0.2979,
      "fold": 0.7021
    },
    "85o": {
      "raise": 0.9128,
      "fold": 0.0872
    },
    "86o": {
      "raise": 0.9434,
      "fold": 0.0566
    },
    "87o": {
      "raise": 0.9673,
      "fold": 0.0327
    },
    "88": {
      "raise": 0.985,
      "fold": 0.015
    },
    "98s": {
      "raise": 0.98,
      "fold": 0.02
    },
    "T8s": {
      "raise": 0.9861,
      "fold": 0.0139
    },
    "J8s": {
      "raise": 0.9809,
      "fold": 0.0191
    },
    "Q8s": {
      "raise": 0.9863,
      "fold": 0.0137
    },
    "K8s": {
      "raise": 0.9888,
      "fold": 0.0112
    },
    "A8s": {
      "raise": 0.9805,
      "fold": 0.0195
    },
    "92o": {
      "raise": 0.0641,
      "fold": 0.9359
    },
    "93o": {
      "raise": 0.1318,
      "fold": 0.8682
    },
    "94o": {
      "raise": 0.813,
      "fold": 0.187
    },
    "95o": {
      "raise": 0.925,
      "fold": 0.075
    },
    "96o": {
      "raise": 0.9647,
      "fold": 0.0353
    },
    "97o": {
      "raise": 0.9755,
      "fold": 0.0245
    },
    "98o": {
      "raise": 0.9815,
      "fold": 0.0185
    },
    "99": {
      "raise": 0.9885,
      "fold": 0.0115
    },
    "T9s": {
      "raise": 0.9811,
      "fold": 0.0189
    },
    "J9s": {
      "raise": 0.9858,
      "fold": 0.0142
    },
    "Q9s": {
      "raise": 0.9843,
      "fold": 0.0157
    },
    "K9s": {
      "raise": 0.9798,
      "fold": 0.0202
    },
    "A9s": {
      "raise": 0.985,
      "fold": 0.015
    },
    "T2o": {
      "raise": 0.071,
      "fold": 0.929
    },
    "T3o": {
      "raise": 0.1967,
      "fold": 0.8033
    },
    "T4o": {
      "raise": 0.771,
      "fold": 0.229
    },
    "T5o": {
      "raise": 0.9245,
      "fold": 0.0755
    },
    "T6o": {
      "raise": 0.9624,
      "fold": 0.0376
    },
    "T7o": {
      "raise": 0.9798,
      "fold": 0.0202
    },
    "T8o": {
      "raise": 0.9883,
      "fold": 0.0117
    },
    "T9o": {
      "raise": 0.9908,
      "fold": 0.0092
    },
    "TT": {
      "raise": 0.9889,
      "fold": 0.0111
    },
    "JTs": {
      "raise": 0.9851,
      "fold": 0.0149
    },
    "QTs": {
      "raise": 0.9837,
      "fold": 0.0163
    },
    "KTs": {
      "raise": 0.9915,
      "fold": 0.0085
    },
    "ATs": {
      "raise": 0.9886,
      "fold": 0.0114
    },
    "J2o": {
      "raise": 0.0979,
      "fold": 0.9021
    },
    "J3o": {
      "raise": 0.5378,
      "fold": 0.4622
    },
    "J4o": {
      "raise": 0.815,
      "fold": 0.185
    },
    "J5o": {
      "raise": 0.9443,
      "fold": 0.0557
    },
    "J6o": {
      "raise": 0.9741,
      "fold": 0.0259
    },
    "J7o": {
      "raise": 0.9826,
      "fold": 0.0174
    },
    "J8o": {
      "raise": 0.9883,
      "fold": 0.0117
    },
    "J9o": {
      "raise": 0.9917,
      "fold": 0.0083
    },
    "JTo": {
      "raise": 0.9915,
      "fold": 0.0085
    },
    "JJ": {
      "raise": 0.9929,
      "fold": 0.0071
    },
    "QJs": {
      "raise": 0.9889,
      "fold": 0.0111
    },
    "KJs": {
      "raise": 0.9932,
      "fold": 0.0068
    },
    "AJs": {
      "raise": 0.9952,
      "fold": 0.0048
    },
    "Q2o": {
      "raise": 0.1615,
      "fold": 0.8385
    },
    "Q3o": {
      "raise": 0.8144,
      "fold": 0.1856
    },
    "Q4o": {
      "raise": 0.9345,
      "fold": 0.0655
    },
    "Q5o": {
      "raise": 0.9475,
      "fold": 0.0525
    },
    "Q6o": {
      "raise": 0.9799,
      "fold": 0.0201
    },
    "Q7o": {
      "raise": 0.983,
      "fold": 0.017
    },
    "Q8o": {
      "raise": 0.9901,
      "fold": 0.0099
    },
    "Q9o": {
      "raise": 0.9913,
      "fold": 0.0087
    },
    "QTo": {
      "raise": 0.99,
      "fold": 0.01
    },
    "QJo": {
      "raise": 0.9922,
      "fold": 0.0078
    },
    "QQ": {
      "raise": 0.9977,
      "fold": 0.0023
    },
    "KQs": {
      "raise": 0.9947,
      "fold": 0.0053
    },
    "AQs": {
      "raise": 0.9983,
      "fold": 0.0017
    },
    "K2o": {
      "raise": 0.1233,
      "fold": 0.8767
    },
    "K3o": {
      "raise": 0.8176,
      "fold": 0.1824
    },
    "K4o": {
      "raise": 0.9134,
      "fold": 0.0866
    },
    "K5o": {
      "raise": 0.9562,
      "fold": 0.0438
    },
    "K6o": {
      "raise": 0.9803,
      "fold": 0.0197
    },
    "K7o": {
      "raise": 0.9873,
      "fold": 0.0127
    },
    "K8o": {
      "raise": 0.9901,
      "fold": 0.0099
    },
    "K9o": {
      "raise": 0.9943,
      "fold": 0.0057
    },
    "KTo": {
      "raise": 0.9915,
      "fold": 0.0085
    },
    "KJo": {
      "raise": 0.9939,
      "fold": 0.0061
    },
    "KQo": {
      "raise": 0.9957,
      "fold": 0.0043
    },
    "KK": {
      "raise": 0.9989,
      "fold": 0.0011
    },
    "AKs": {
      "raise": 0.9983,
      "fold": 0.0017
    },
    "A2o": {
      "raise": 0.5216,
      "fold": 0.4784
    },
    "A3o": {
      "raise": 0.8713,
      "fold": 0.1287
    },
    "A4o": {
      "raise": 0.9468,
      "fold": 0.0532
    },
    "A5o": {
      "raise": 0.9687,
      "fold": 0.0313
    },
    "A6o": {
      "raise": 0.9821,
      "fold": 0.0179
    },
    "A7o": {
      "raise": 0.9864,
      "fold": 0.0136
    },
    "A8o": {
      "raise": 0.9921,
      "fold": 0.0079
    },
    "A9o": {
      "raise": 0.9936,
      "fold": 0.0064
    },
    "ATo": {
      "raise": 0.9934,
      "fold": 0.0066
    },
    "AJo": {
      "raise": 0.994,
      "fold": 0.006
    },
    "AQo": {
      "raise": 0.998,
      "fold": 0.002
    },
    "AKo": {
      "raise": 0.9983,
      "fold": 0.0017
    },
    "AA": {
      "raise": 0.9989,
      "fold": 0.0011
    }
  },
  "BB_vs_BTN": {
    "22": {
      "fold": 0.9862,
      "call": 0.0037,
      "3bet": 0.0101
    },
    "32s": {
      "fold": 0.9843,
      "call": 0.0039,
      "3bet": 0.0117
    },
    "42s": {
      "fold": 0.9837,
      "call": 0.0098,
      "3bet": 0.0064
    },
    "52s": {
      "fold": 0.9851,
      "call": 0.0063,
      "3bet": 0.0087
    },
    "62s": {
      "fold": 0.9772,
      "call": 0.0123,
      "3bet": 0.0104
    },
    "72s": {
      "fold": 0.9679,
      "call": 0.0209,
      "3bet": 0.0112
    },
    "82s": {
      "fold": 0.9542,
      "call": 0.0307,
      "3bet": 0.0151
    },
    "92s": {
      "fold": 0.9277,
      "call": 0.0615,
      "3bet": 0.0108
    },
    "T2s": {
      "fold": 0.8589,
      "call": 0.1274,
      "3bet": 0.0138
    },
    "J2s": {
      "fold": 0.6277,
      "call": 0.3645,
      "3bet": 0.0078
    },
    "Q2s": {
      "fold": 0.4578,
      "call": 0.5353,
      "3bet": 0.0069
    },
    "K2s": {
      "fold": 0.1171,
      "call": 0.8736,
      "3bet": 0.0092
    },
    "A2s": {
      "fold": 0.052,
      "call": 0.9184,
      "3bet": 0.0296
    },
    "32o": {
      "fold": 0.9945,
      "call": 0.0009,
      "3bet": 0.0046
    },
    "33": {
      "fold": 0.9562,
      "call": 0.0367,
      "3bet": 0.007
    },
    "43s": {
      "fold": 0.9795,
      "call": 0.0146,
      "3bet": 0.0059
    },
    "53s": {
      "fold": 0.9468,
      "call": 0.0404,
      "3bet": 0.0128
    },
    "63s": {
      "fold": 0.8792,
      "call": 0.1129,
      "3bet": 0.0079
    },
    "73s": {
      "fold": 0.8729,
      "call": 0.1069,
      "3bet": 0.0202
    },
    "83s": {
      "fold": 0.7544,
      "call": 0.235,
      "3bet": 0.0106
    },
    "93s": {
      "fold": 0.1518,
      "call": 0.8377,
      "3bet": 0.0104
    },
    "T3s": {
      "fold": 0.1011,
      "call": 0.8906,
      "3bet": 0.0083
    },
    "J3s": {
      "fold": 0.0528,
      "call": 0.9339,
      "3bet": 0.0133
    },
    "Q3s": {
      "fold": 0.04,
      "call": 0.9439,
      "3bet": 0.0161
    },
    "K3s": {
      "fold": 0.0296,
      "call": 0.949,
      "3bet": 0.0213
    },
    "A3s": {
      "fold": 0.0399,
      "call": 0.9343,
      "3bet": 0.0259
    },
    "42o": {
      "fold": 0.9948,
      "call": 0.0014,
      "3bet": 0.0037
    },
    "43o": {
      "fold": 0.9878,
      "call": 0.0061,
      "3bet": 0.0061
    },
    "44": {
      "fold": 0.2262,
      "call": 0.7641,
      "3bet": 0.0096
    },
    "54s": {
      "fold": 0.2286,
      "call": 0.7636,
      "3bet": 0.0078
    },
    "64s": {
      "fold": 0.2791,
      "call": 0.7073,
      "3bet": 0.0137
    },
    "74s": {
      "fold": 0.1052,
      "call": 0.8852,
      "3bet": 0.0096
    },
    "84s": {
      "fold": 0.0259,
      "call": 0.9554,
      "3bet": 0.0187
    },
    "94s": {
      "fold": 0.027,
      "call": 0.9553,
      "3bet": 0.0177
    },
    "T4s": {
      "fold": 0.0325,
      "call": 0.949,
      "3bet": 0.0185
    },
    "J4s": {
      "fold": 0.0428,
      "call": 0.9364,
      "3bet": 0.0208
    },
    "Q4s": {
      "fold": 0.0246,
      "call": 0.9426,
      "3bet": 0.0329
    },
    "K4s": {
      "fold": 0.0195,
      "call": 0.9388,
      "3bet": 0.0417
    },
    "A4s": {
      "fold": 0.0097,
      "call": 0.927,
      "3bet": 0.0633
    },
    "52o": {
      "fold": 0.9932,
      "call": 0.0012,
      "3bet": 0.0056
    },
    "53o": {
      "fold": 0.9855,
      "call": 0.0092,
      "3bet": 0.0052
    },
    "54o": {
      "fold": 0.9597,
      "call": 0.0332,
      "3bet": 0.0072
    },
    "55": {
      "fold": 0.0223,
      "call": 0.9534,
      "3bet": 0.0243
    },
    "65s": {
      "fold": 0.0342,
      "call": 0.944,
      "3bet": 0.0219
    },
    "75s": {
      "fold": 0.0248,
      "call": 0.9552,
      "3bet": 0.0201
    },
    "85s": {
      "fold": 0.0433,
      "call": 0.9366,
      "3bet": 0.0201
    },
    "95s": {
      "fold": 0.0167,
      "call": 0.9542,
      "3bet": 0.0291
    },
    "T5s": {
      "fold": 0.0151,
      "call": 0.9182,
      "3bet": 0.0667
    },
    "J5s": {
      "fold": 0.0122,
      "call": 0.9436,
      "3bet": 0.0442
    },
    "Q5s": {
      "fold": 0.0218,
      "call": 0.8719,
      "3bet": 0.1063
    },
    "K5s": {
      "fold": 0.0126,
      "call": 0.8962,
      "3bet": 0.0913
    },
    "A5s": {
      "fold": 0.0101,
      "call": 0.8963,
      "3bet": 0.0936
    },
    "62o": {
      "fold": 0.9912,
      "call": 0.0037,
      "3bet": 0.0051
    },
    "63o": {
      "fold": 0.9753,
      "call": 0.0168,
      "3bet": 0.0079
    },
    "64o": {
      "fold": 0.9003,
      "call": 0.0929,
      "3bet": 0.0068
    },
    "65o": {
      "fold": 0.0613,
      "call": 0.9316,
      "3bet": 0.0071
    },
    "66": {
      "fold": 0.0094,
      "call": 0.9436,
      "3bet": 0.047
    },
    "76s": {
      "fold": 0.015,
      "call": 0.9257,
      "3bet": 0.0594
    },
    "86s": {
      "fold": 0.0197,
      "call": 0.9369,
      "3bet": 0.0433
    },
    "96s": {
      "fold": 0.024,
      "call": 0.8873,
      "3bet": 0.0886
    },
    "T6s": {
      "fold": 0.0172,
      "call": 0.8838,
      "3bet": 0.099
    },
    "J6s": {
      "fold": 0.0156,
      "call": 0.8835,
      "3bet": 0.1009
    },
    "Q6s": {
      "fold": 0.0115,
      "call": 0.8857,
      "3bet": 0.1028
    },
    "K6s": {
      "fold": 0.0173,
      "call": 0.8368,
      "3bet": 0.1459
    },
    "A6s": {
      "fold": 0.0192,
      "call": 0.5834,
      "3bet": 0.3974
    },
    "72o": {
      "fold": 0.9893,
      "call": 0.0055,
      "3bet": 0.0052
    },
    "73o": {
      "fold": 0.9705,
      "call": 0.0233,
      "3bet": 0.0062
    },
    "74o": {
      "fold": 0.6747,
      "call": 0.3185,
      "3bet": 0.0069
    },
    "75o": {
      "fold": 0.0339,
      "call": 0.9564,
      "3bet": 0.0097
    },
    "76o": {
      "fold": 0.009,
      "call": 0.9725,
      "3bet": 0.0186
    },
    "77": {
      "fold": 0.0095,
      "call": 0.8831,
      "3bet": 0.1074
    },
    "87s": {
      "fold": 0.0164,
      "call": 0.8281,
      "3bet": 0.1555
    },
    "97s": {
      "fold": 0.0203,
      "call": 0.8665,
      "3bet": 0.1133
    },
    "T7s": {
      "fold": 0.0119,
      "call": 0.8014,
      "3bet": 0.1868
    },
    "J7s": {
      "fold": 0.0226,
      "call": 0.6387,
      "3bet": 0.3387
    },
    "Q7s": {
      "fold": 0.0131,
      "call": 0.7569,
      "3bet": 0.23
    },
    "K7s": {
      "fold": 0.0168,
      "call": 0.6354,
      "3bet": 0.3478
    },
    "A7s": {
      "fold": 0.0225,
      "call": 0.1958,
      "3bet": 0.7817
    },
    "82o": {
      "fold": 0.9892,
      "call": 0.0051,
      "3bet": 0.0057
    },
    "83o": {
      "fold": 0.9543,
      "call": 0.0393,
      "3bet": 0.0064
    },
    "84o": {
      "fold": 0.1173,
      "call": 0.8769,
      "3bet": 0.0057
    },
    "85o": {
      "fold": 0.0218,
      "call": 0.9625,
      "3bet": 0.0157
    },
    "86o": {
      "fold": 0.0123,
      "call": 0.9679,
      "3bet": 0.0197
    },
    "87o": {
      "fold": 0.0091,
      "call": 0.9421,
      "3bet": 0.0488
    },
    "88": {
      "fold": 0.02,
      "call": 0.3931,
      "3bet": 0.5869
    },
    "98s": {
      "fold": 0.0199,
      "call": 0.5555,
      "3bet": 0.4245
    },
    "T8s": {
      "fold": 0.0132,
      "call": 0.47,
      "3bet": 0.5167
    },
    "J8s": {
      "fold": 0.0198,
      "call": 0.4558,
      "3bet": 0.5244
    },
    "Q8s": {
      "fold": 0.0235,
      "call": 0.1684,
      "3bet": 0.8081
    },
    "K8s": {
      "fold": 0.0185,
      "call": 0.1438,
      "3bet": 0.8377
    },
    "A8s": {
      "fold": 0.0106,
      "call": 0.0903,
      "3bet": 0.8992
    },
    "92o": {
      "fold": 0.9851,
      "call": 0.009,
      "3bet": 0.0059
    },
    "93o": {
      "fold": 0.9337,
      "call": 0.0595,
      "3bet": 0.0068
    },
    "94o": {
      "fold": 0.0549,
      "call": 0.9363,
      "3bet": 0.0088
    },
    "95o": {
      "fold": 0.0151,
      "call": 0.9714,
      "3bet": 0.0134
    },
    "96o": {
      "fold": 0.0084,
      "call": 0.9632,
      "3bet": 0.0285
    },
    "97o": {
      "fold": 0.0061,
      "call": 0.9409,
      "3bet": 0.053
    },
    "98o": {
      "fold": 0.0034,
      "call": 0.9108,
      "3bet": 0.0858
    },
    "99": {
      "fold": 0.0192,
      "call": 0.1094,
      "3bet": 0.8714
    },
    "T9s": {
      "fold": 0.0219,
      "call": 0.2988,
      "3bet": 0.6794
    },
    "J9s": {
      "fold": 0.0141,
      "call": 0.0974,
      "3bet": 0.8885
    },
    "Q9s": {
      "fold": 0.0193,
      "call": 0.1196,
      "3bet": 0.8611
    },
    "K9s": {
      "fold": 0.0126,
      "call": 0.0472,
      "3bet": 0.9402
    },
    "A9s": {
      "fold": 0.0098,
      "call": 0.0359,
      "3bet": 0.9543
    },
    "T2o": {
      "fold": 0.981,
      "call": 0.0126,
      "3bet": 0.0063
    },
    "T3o": {
      "fold": 0.5647,
      "call": 0.4285,
      "3bet": 0.0068
    },
    "T4o": {
      "fold": 0.0241,
      "call": 0.9656,
      "3bet": 0.0102
    },
    "T5o": {
      "fold": 0.0163,
      "call": 0.9688,
      "3bet": 0.015
    },
    "T6o": {
      "fold": 0.0066,
      "call": 0.9618,
      "3bet": 0.0317
    },
    "T7o": {
      "fold": 0.0039,
      "call": 0.9138,
      "3bet": 0.0824
    },
    "T8o": {
      "fold": 0.0075,
      "call": 0.798,
      "3bet": 0.1945
    },
    "T9o": {
      "fold": 0.0171,
      "call": 0.1826,
      "3bet": 0.8003
    },
    "TT": {
      "fold": 0.0088,
      "call": 0.0435,
      "3bet": 0.9477
    },
    "JTs": {
      "fold": 0.0125,
      "call": 0.0473,
      "3bet": 0.9401
    },
    "QTs": {
      "fold": 0.0089,
      "call": 0.0515,
      "3bet": 0.9396
    },
    "KTs": {
      "fold": 0.0061,
      "call": 0.0222,
      "3bet": 0.9717
    },
    "ATs": {
      "fold": 0.0064,
      "call": 0.0284,
      "3bet": 0.9652
    },
    "J2o": {
      "fold": 0.9636,
      "call": 0.0299,
      "3bet": 0.0064
    },
    "J3o": {
      "fold": 0.0797,
      "call": 0.9145,
      "3bet": 0.0058
    },
    "J4o": {
      "fold": 0.0174,
      "call": 0.9713,
      "3bet": 0.0113
    },
    "J5o": {
      "fold": 0.0125,
      "call": 0.9681,
      "3bet": 0.0194
    },
    "J6o": {
      "fold": 0.0055,
      "call": 0.9349,
      "3bet": 0.0596
    },
    "J7o": {
      "fold": 0.0078,
      "call": 0.8813,
      "3bet": 0.1109
    },
    "J8o": {
      "fold": 0.0117,
      "call": 0.44,
      "3bet": 0.5483
    },
    "J9o": {
      "fold": 0.017,
      "call": 0.1626,
      "3bet": 0.8204
    },
    "JTo": {
      "fold": 0.0087,
      "call": 0.0368,
      "3bet": 0.9545
    },
    "JJ": {
      "fold": 0.0017,
      "call": 0.0097,
      "3bet": 0.9886
    },
    "QJs": {
      "fold": 0.0045,
      "call": 0.0181,
      "3bet": 0.9773
    },
    "KJs": {
      "fold": 0.0028,
      "call": 0.0121,
      "3bet": 0.9851
    },
    "AJs": {
      "fold": 0.005,
      "call": 0.0162,
      "3bet": 0.9788
    },
    "Q2o": {
      "fold": 0.9192,
      "call": 0.0678,
      "3bet": 0.013
    },
    "Q3o": {
      "fold": 0.0417,
      "call": 0.9421,
      "3bet": 0.0162
    },
    "Q4o": {
      "fold": 0.0108,
      "call": 0.9669,
      "3bet": 0.0223
    },
    "Q5o": {
      "fold": 0.0078,
      "call": 0.9621,
      "3bet": 0.03
    },
    "Q6o": {
      "fold": 0.0088,
      "call": 0.9284,
      "3bet": 0.0628
    },
    "Q7o": {
      "fold": 0.0049,
      "call": 0.8841,
      "3bet": 0.1111
    },
    "Q8o": {
      "fold": 0.014,
      "call": 0.3075,
      "3bet": 0.6785
    },
    "Q9o": {
      "fold": 0.0151,
      "call": 0.1263,
      "3bet": 0.8587
    },
    "QTo": {
      "fold": 0.0065,
      "call": 0.0324,
      "3bet": 0.9611
    },
    "QJo": {
      "fold": 0.0043,
      "call": 0.0232,
      "3bet": 0.9725
    },
    "QQ": {
      "fold": 0.0015,
      "call": 0.0062,
      "3bet": 0.9923
    },
    "KQs": {
      "fold": 0.0019,
      "call": 0.0126,
      "3bet": 0.9854
    },
    "AQs": {
      "fold": 0.0019,
      "call": 0.0105,
      "3bet": 0.9876
    },
    "K2o": {
      "fold": 0.5377,
      "call": 0.454,
      "3bet": 0.0083
    },
    "K3o": {
      "fold": 0.0227,
      "call": 0.9683,
      "3bet": 0.009
    },
    "K4o": {
      "fold": 0.0122,
      "call": 0.9692,
      "3bet": 0.0186
    },
    "K5o": {
      "fold": 0.0084,
      "call": 0.9624,
      "3bet": 0.0292
    },
    "K6o": {
      "fold": 0.0057,
      "call": 0.9309,
      "3bet": 0.0634
    },
    "K7o": {
      "fold": 0.0102,
      "call": 0.716,
      "3bet": 0.2738
    },
    "K8o": {
      "fold": 0.0128,
      "call": 0.2423,
      "3bet": 0.7449
    },
    "K9o": {
      "fold": 0.0131,
      "call": 0.0829,
      "3bet": 0.904
    },
    "KTo": {
      "fold": 0.0048,
      "call": 0.0195,
      "3bet": 0.9757
    },
    "KJo": {
      "fold": 0.0032,
      "call": 0.014,
      "3bet": 0.9827
    },
    "KQo": {
      "fold": 0.0013,
      "call": 0.0065,
      "3bet": 0.9922
    },
    "KK": {
      "fold": 0.0007,
      "call": 0.0037,
      "3bet": 0.9955
    },
    "AKs": {
      "fold": 0.0011,
      "call": 0.0017,
      "3bet": 0.9971
    },
    "A2o": {
      "fold": 0.1071,
      "call": 0.8864,
      "3bet": 0.0064
    },
    "A3o": {
      "fold": 0.0184,
      "call": 0.9679,
      "3bet": 0.0137
    },
    "A4o": {
      "fold": 0.0073,
      "call": 0.9772,
      "3bet": 0.0155
    },
    "A5o": {
      "fold": 0.0048,
      "call": 0.9549,
      "3bet": 0.0403
    },
    "A6o": {
      "fold": 0.0043,
      "call": 0.9029,
      "3bet": 0.0928
    },
    "A7o": {
      "fold": 0.0103,
      "call": 0.5004,
      "3bet": 0.4893
    },
    "A8o": {
      "fold": 0.0136,
      "call": 0.1271,
      "3bet": 0.8593
    },
    "A9o": {
      "fold": 0.0107,
      "call": 0.0663,
      "3bet": 0.923
    },
    "ATo": {
      "fold": 0.0052,
      "call": 0.0205,
      "3bet": 0.9743
    },
    "AJo": {
      "fold": 0.0027,
      "call": 0.0111,
      "3bet": 0.9863
    },
    "AQo": {
      "fold": 0.0013,
      "call": 0.0053,
      "3bet": 0.9934
    },
    "AKo": {
      "fold": 0.0008,
      "call": 0.0051,
      "3bet": 0.9941
    },
    "AA": {
      "fold": 0.0016,
      "call": 0.0039,
      "3bet": 0.9946
    }
  },
  "BTN_vs_3bet": {
    "22": {
      "fold": 0.9611,
      "call": 0.0234,
      "4bet": 0.0154
    },
    "32s": {
      "fold": 0.9261,
      "call": 0.0219,
      "4bet": 0.052
    },
    "42s": {
      "fold": 0.9678,
      "call": 0.0166,
      "4bet": 0.0156
    },
    "52s": {
      "fold": 0.8663,
      "call": 0.1196,
      "4bet": 0.0142
    },
    "62s": {
      "fold": 0.8807,
      "call": 0.1038,
      "4bet": 0.0155
    },
    "72s": {
      "fold": 0.9062,
      "call": 0.0427,
      "4bet": 0.0511
    },
    "82s": {
      "fold": 0.6842,
      "call": 0.2946,
      "4bet": 0.0211
    },
    "92s": {
      "fold": 0.4853,
      "call": 0.4648,
      "4bet": 0.0498
    },
    "T2s": {
      "fold": 0.1468,
      "call": 0.8252,
      "4bet": 0.028
    },
    "J2s": {
      "fold": 0.0462,
      "call": 0.931,
      "4bet": 0.0228
    },
    "Q2s": {
      "fold": 0.0079,
      "call": 0.9899,
      "4bet": 0.0022
    },
    "K2s": {
      "fold": 0.0079,
      "call": 0.9786,
      "4bet": 0.0135
    },
    "A2s": {
      "fold": 0.006,
      "call": 0.9697,
      "4bet": 0.0243
    },
    "32o": {
      "fold": 0.9773,
      "call": 0.0126,
      "4bet": 0.0101
    },
    "33": {
      "fold": 0.6447,
      "call": 0.2935,
      "4bet": 0.0618
    },
    "43s": {
      "fold": 0.8456,
      "call": 0.1361,
      "4bet": 0.0183
    },
    "53s": {
      "fold": 0.6552,
      "call": 0.3353,
      "4bet": 0.0095
    },
    "63s": {
      "fold": 0.49,
      "call": 0.4897,
      "4bet": 0.0203
    },
    "73s": {
      "fold": 0.2645,
      "call": 0.6816,
      "4bet": 0.0539
    },
    "83s": {
      "fold": 0.0249,
      "call": 0.9523,
      "4bet": 0.0228
    },
    "93s": {
      "fold": 0.012,
      "call": 0.9814,
      "4bet": 0.0066
    },
    "T3s": {
      "fold": 0.0039,
      "call": 0.9869,
      "4bet": 0.0092
    },
    "J3s": {
      "fold": 0.0034,
      "call": 0.9862,
      "4bet": 0.0104
    },
    "Q3s": {
      "fold": 0.0017,
      "call": 0.977,
      "4bet": 0.0213
    },
    "K3s": {
      "fold": 0.0019,
      "call": 0.974,
      "4bet": 0.0241
    },
    "A3s": {
      "fold": 0.0027,
      "call": 0.9804,
      "4bet": 0.0169
    },
    "42o": {
      "fold": 0.8581,
      "call": 0.0145,
      "4bet": 0.1273
    },
    "43o": {
      "fold": 0.9509,
      "call": 0.0127,
      "4bet": 0.0364
    },
    "44": {
      "fold": 0.0047,
      "call": 0.982,
      "4bet": 0.0133
    },
    "54s": {
      "fold": 0.0347,
      "call": 0.8779,
      "4bet": 0.0873
    },
    "64s": {
      "fold": 0.0086,
      "call": 0.9726,
      "4bet": 0.0188
    },
    "74s": {
      "fold": 0.005,
      "call": 0.9841,
      "4bet": 0.0108
    },
    "84s": {
      "fold": 0.0111,
      "call": 0.9789,
      "4bet": 0.01
    },
    "94s": {
      "fold": 0.0034,
      "call": 0.9899,
      "4bet": 0.0067
    },
    "T4s": {
      "fold": 0.002,
      "call": 0.991,
      "4bet": 0.007
    },
    "J4s": {
      "fold": 0.0013,
      "call": 0.9874,
      "4bet": 0.0114
    },
    "Q4s": {
      "fold": 0.002,
      "call": 0.9924,
      "4bet": 0.0056
    },
    "K4s": {
      "fold": 0.0016,
      "call": 0.9767,
      "4bet": 0.0217
    },
    "A4s": {
      "fold": 0.0005,
      "call": 0.9827,
      "4bet": 0.0168
    },
    "52o": {
      "fold": 0.968,
      "call": 0.0087,
      "4bet": 0.0233
    },
    "53o": {
      "fold": 0.9024,
      "call": 0.0337,
      "4bet": 0.0638
    },
    "54o": {
      "fold": 0.4134,
      "call": 0.5535,
      "4bet": 0.0331
    },
    "55": {
      "fold": 0.0038,
      "call": 0.9854,
      "4bet": 0.0108
    },
    "65s": {
      "fold": 0.0068,
      "call": 0.9803,
      "4bet": 0.0129
    },
    "75s": {
      "fold": 0.0021,
      "call": 0.9817,
      "4bet": 0.0162
    },
    "85s": {
      "fold": 0.0013,
      "call": 0.9675,
      "4bet": 0.0312
    },
    "95s": {
      "fold": 0.001,
      "call": 0.9764,
      "4bet": 0.0226
    },
    "T5s": {
      "fold": 0.0029,
      "call": 0.9732,
      "4bet": 0.0239
    },
    "J5s": {
      "fold": 0.0013,
      "call": 0.9825,
      "4bet": 0.0162
    },
    "Q5s": {
      "fold": 0.0016,
      "call": 0.9809,
      "4bet": 0.0175
    },
    "K5s": {
      "fold": 0.0009,
      "call": 0.9649,
      "4bet": 0.0342
    },
    "A5s": {
      "fold": 0.003,
      "call": 0.9791,
      "4bet": 0.0179
    },
    "62o": {
      "fold": 0.9261,
      "call": 0.0542,
      "4bet": 0.0197
    },
    "63o": {
      "fold": 0.872,
      "call": 0.0251,
      "4bet": 0.103
    },
    "64o": {
      "fold": 0.0135,
      "call": 0.9282,
      "4bet": 0.0583
    },
    "65o": {
      "fold": 0.0016,
      "call": 0.9792,
      "4bet": 0.0192
    },
    "66": {
      "fold": 0.0006,
      "call": 0.9821,
      "4bet": 0.0173
    },
    "76s": {
      "fold": 0.0048,
      "call": 0.9785,
      "4bet": 0.0167
    },
    "86s": {
      "fold": 0.0033,
      "call": 0.9573,
      "4bet": 0.0394
    },
    "96s": {
      "fold": 0.0006,
      "call": 0.98,
      "4bet": 0.0194
    },
    "T6s": {
      "fold": 0.0012,
      "call": 0.9704,
      "4bet": 0.0284
    },
    "J6s": {
      "fold": 0.0005,
      "call": 0.9286,
      "4bet": 0.0709
    },
    "Q6s": {
      "fold": 0.0017,
      "call": 0.9546,
      "4bet": 0.0437
    },
    "K6s": {
      "fold": 0.0019,
      "call": 0.9429,
      "4bet": 0.0553
    },
    "A6s": {
      "fold": 0.0016,
      "call": 0.9532,
      "4bet": 0.0452
    },
    "72o": {
      "fold": 0.9454,
      "call": 0.0154,
      "4bet": 0.0392
    },
    "73o": {
      "fold": 0.9012,
      "call": 0.0589,
      "4bet": 0.04
    },
    "74o": {
      "fold": 0.0162,
      "call": 0.9679,
      "4bet": 0.0159
    },
    "75o": {
      "fold": 0.0008,
      "call": 0.9946,
      "4bet": 0.0046
    },
    "76o": {
      "fold": 0.0003,
      "call": 0.9879,
      "4bet": 0.0119
    },
    "77": {
      "fold": 0.0007,
      "call": 0.9854,
      "4bet": 0.0139
    },
    "87s": {
      "fold": 0.0012,
      "call": 0.9655,
      "4bet": 0.0333
    },
    "97s": {
      "fold": 0.0007,
      "call": 0.9322,
      "4bet": 0.0671
    },
    "T7s": {
      "fold": 0.0006,
      "call": 0.9458,
      "4bet": 0.0536
    },
    "J7s": {
      "fold": 0.0006,
      "call": 0.9196,
      "4bet": 0.0798
    },
    "Q7s": {
      "fold": 0.0006,
      "call": 0.9314,
      "4bet": 0.0681
    },
    "K7s": {
      "fold": 0.0006,
      "call": 0.8719,
      "4bet": 0.1275
    },
    "A7s": {
      "fold": 0.0005,
      "call": 0.9201,
      "4bet": 0.0794
    },
    "82o": {
      "fold": 0.8492,
      "call": 0.067,
      "4bet": 0.0838
    },
    "83o": {
      "fold": 0.5325,
      "call": 0.4412,
      "4bet": 0.0263
    },
    "84o": {
      "fold": 0.0045,
      "call": 0.9906,
      "4bet": 0.0048
    },
    "85o": {
      "fold": 0.0004,
      "call": 0.9921,
      "4bet": 0.0075
    },
    "86o": {
      "fold": 0.0003,
      "call": 0.9887,
      "4bet": 0.011
    },
    "87o": {
      "fold": 0.001,
      "call": 0.9904,
      "4bet": 0.0087
    },
    "88": {
      "fold": 0.0005,
      "call": 0.9492,
      "4bet": 0.0503
    },
    "98s": {
      "fold": 0.0006,
      "call": 0.938,
      "4bet": 0.0614
    },
    "T8s": {
      "fold": 0.0006,
      "call": 0.8913,
      "4bet": 0.1082
    },
    "J8s": {
      "fold": 0.0029,
      "call": 0.8718,
      "4bet": 0.1254
    },
    "Q8s": {
      "fold": 0.0042,
      "call": 0.8834,
      "4bet": 0.1124
    },
    "K8s": {
      "fold": 0.0005,
      "call": 0.8249,
      "4bet": 0.1746
    },
    "A8s": {
      "fold": 0.0006,
      "call": 0.8583,
      "4bet": 0.1412
    },
    "92o": {
      "fold": 0.9099,
      "call": 0.0822,
      "4bet": 0.0079
    },
    "93o": {
      "fold": 0.0736,
      "call": 0.8477,
      "4bet": 0.0788
    },
    "94o": {
      "fold": 0.0008,
      "call": 0.9916,
      "4bet": 0.0076
    },
    "95o": {
      "fold": 0.0016,
      "call": 0.9888,
      "4bet": 0.0096
    },
    "96o": {
      "fold": 0.0003,
      "call": 0.987,
      "4bet": 0.0127
    },
    "97o": {
      "fold": 0.0002,
      "call": 0.9794,
      "4bet": 0.0204
    },
    "98o": {
      "fold": 0.0002,
      "call": 0.9804,
      "4bet": 0.0194
    },
    "99": {
      "fold": 0.0004,
      "call": 0.8305,
      "4bet": 0.1691
    },
    "T9s": {
      "fold": 0.0006,
      "call": 0.8412,
      "4bet": 0.1581
    },
    "J9s": {
      "fold": 0.0016,
      "call": 0.7167,
      "4bet": 0.2817
    },
    "Q9s": {
      "fold": 0.0019,
      "call": 0.6075,
      "4bet": 0.3906
    },
    "K9s": {
      "fold": 0.0016,
      "call": 0.2028,
      "4bet": 0.7956
    },
    "A9s": {
      "fold": 0.0005,
      "call": 0.2106,
      "4bet": 0.7889
    },
    "T2o": {
      "fold": 0.8407,
      "call": 0.1282,
      "4bet": 0.0311
    },
    "T3o": {
      "fold": 0.0157,
      "call": 0.9746,
      "4bet": 0.0097
    },
    "T4o": {
      "fold": 0.0008,
      "call": 0.9942,
      "4bet": 0.005
    },
    "T5o": {
      "fold": 0.0004,
      "call": 0.9921,
      "4bet": 0.0075
    },
    "T6o": {
      "fold": 0.0006,
      "call": 0.987,
      "4bet": 0.0124
    },
    "T7o": {
      "fold": 0.0003,
      "call": 0.9819,
      "4bet": 0.0177
    },
    "T8o": {
      "fold": 0.0002,
      "call": 0.9572,
      "4bet": 0.0426
    },
    "T9o": {
      "fold": 0.0002,
      "call": 0.9418,
      "4bet": 0.058
    },
    "TT": {
      "fold": 0.0004,
      "call": 0.1277,
      "4bet": 0.8719
    },
    "JTs": {
      "fold": 0.0017,
      "call": 0.2219,
      "4bet": 0.7764
    },
    "QTs": {
      "fold": 0.0017,
      "call": 0.1375,
      "4bet": 0.8608
    },
    "KTs": {
      "fold": 0.0005,
      "call": 0.0571,
      "4bet": 0.9424
    },
    "ATs": {
      "fold": 0.0018,
      "call": 0.0342,
      "4bet": 0.964
    },
    "J2o": {
      "fold": 0.5646,
      "call": 0.416,
      "4bet": 0.0194
    },
    "J3o": {
      "fold": 0.0062,
      "call": 0.9886,
      "4bet": 0.0052
    },
    "J4o": {
      "fold": 0.0006,
      "call": 0.991,
      "4bet": 0.0085
    },
    "J5o": {
      "fold": 0.0006,
      "call": 0.9899,
      "4bet": 0.0095
    },
    "J6o": {
      "fold": 0.0014,
      "call": 0.9881,
      "4bet": 0.0105
    },
    "J7o": {
      "fold": 0.0004,
      "call": 0.9759,
      "4bet": 0.0237
    },
    "J8o": {
      "fold": 0.0002,
      "call": 0.9692,
      "4bet": 0.0306
    },
    "J9o": {
      "fold": 0.0002,
      "call": 0.9045,
      "4bet": 0.0953
    },
    "JTo": {
      "fold": 0.0002,
      "call": 0.5743,
      "4bet": 0.4255
    },
    "JJ": {
      "fold": 0.0004,
      "call": 0.0385,
      "4bet": 0.9612
    },
    "QJs": {
      "fold": 0.0006,
      "call": 0.0454,
      "4bet": 0.954
    },
    "KJs": {
      "fold": 0.003,
      "call": 0.0319,
      "4bet": 0.9651
    },
    "AJs": {
      "fold": 0.0005,
      "call": 0.013,
      "4bet": 0.9864
    },
    "Q2o": {
      "fold": 0.0183,
      "call": 0.9702,
      "4bet": 0.0115
    },
    "Q3o": {
      "fold": 0.0019,
      "call": 0.9941,
      "4bet": 0.0041
    },
    "Q4o": {
      "fold": 0.0022,
      "call": 0.9903,
      "4bet": 0.0076
    },
    "Q5o": {
      "fold": 0.0002,
      "call": 0.9871,
      "4bet": 0.0127
    },
    "Q6o": {
      "fold": 0.0004,
      "call": 0.9723,
      "4bet": 0.0272
    },
    "Q7o": {
      "fold": 0.0002,
      "call": 0.9834,
      "4bet": 0.0164
    },
    "Q8o": {
      "fold": 0.0002,
      "call": 0.9513,
      "4bet": 0.0485
    },
    "Q9o": {
      "fold": 0.0002,
      "call": 0.8985,
      "4bet": 0.1013
    },
    "QTo": {
      "fold": 0.0006,
      "call": 0.1798,
      "4bet": 0.8196
    },
    "QJo": {
      "fold": 0.0002,
      "call": 0.0476,
      "4bet": 0.9522
    },
    "QQ": {
      "fold": 0.0004,
      "call": 0.0054,
      "4bet": 0.9943
    },
    "KQs": {
      "fold": 0.0016,
      "call": 0.0233,
      "4bet": 0.975
    },
    "AQs": {
      "fold": 0.0028,
      "call": 0.015,
      "4bet": 0.9822
    },
    "K2o": {
      "fold": 0.0191,
      "call": 0.9591,
      "4bet": 0.0218
    },
    "K3o": {
      "fold": 0.0008,
      "call": 0.9923,
      "4bet": 0.0069
    },
    "K4o": {
      "fold": 0.0003,
      "call": 0.9936,
      "4bet": 0.0062
    },
    "K5o": {
      "fold": 0.0016,
      "call": 0.9899,
      "4bet": 0.0085
    },
    "K6o": {
      "fold": 0.0011,
      "call": 0.9641,
      "4bet": 0.0348
    },
    "K7o": {
      "fold": 0.0002,
      "call": 0.9617,
      "4bet": 0.0381
    },
    "K8o": {
      "fold": 0.0002,
      "call": 0.9553,
      "4bet": 0.0445
    },
    "K9o": {
      "fold": 0.0002,
      "call": 0.883,
      "4bet": 0.1168
    },
    "KTo": {
      "fold": 0.0002,
      "call": 0.0921,
      "4bet": 0.9077
    },
    "KJo": {
      "fold": 0.0002,
      "call": 0.0277,
      "4bet": 0.9721
    },
    "KQo": {
      "fold": 0.0002,
      "call": 0.0264,
      "4bet": 0.9735
    },
    "KK": {
      "fold": 0.0004,
      "call": 0.0051,
      "4bet": 0.9945
    },
    "AKs": {
      "fold": 0.0006,
      "call": 0.0044,
      "4bet": 0.995
    },
    "A2o": {
      "fold": 0.0051,
      "call": 0.9878,
      "4bet": 0.0071
    },
    "A3o": {
      "fold": 0.0017,
      "call": 0.991,
      "4bet": 0.0074
    },
    "A4o": {
      "fold": 0.0019,
      "call": 0.9906,
      "4bet": 0.0075
    },
    "A5o": {
      "fold": 0.0003,
      "call": 0.9906,
      "4bet": 0.0091
    },
    "A6o": {
      "fold": 0.0003,
      "call": 0.9827,
      "4bet": 0.0171
    },
    "A7o": {
      "fold": 0.0002,
      "call": 0.9745,
      "4bet": 0.0253
    },
    "A8o": {
      "fold": 0.0006,
      "call": 0.9247,
      "4bet": 0.0747
    },
    "A9o": {
      "fold": 0.0002,
      "call": 0.5401,
      "4bet": 0.4597
    },
    "ATo": {
      "fold": 0.0012,
      "call": 0.0815,
      "4bet": 0.9172
    },
    "AJo": {
      "fold": 0.0002,
      "call": 0.0459,
      "4bet": 0.9539
    },
    "AQo": {
      "fold": 0.0002,
      "call": 0.0057,
      "4bet": 0.9941
    },
    "AKo": {
      "fold": 0.0002,
      "call": 0.0056,
      "4bet": 0.9942
    },
    "AA": {
      "fold": 0.0004,
      "call": 0.0004,
      "4bet": 0.9992
    }
  },
  "BB_vs_4bet": {
    "22": {
      "fold": 0.5945,
      "call": 0.4055
    },
    "32s": {
      "fold": 0.9066,
      "call": 0.0934
    },
    "42s": {
      "fold": 0.7704,
      "call": 0.2296
    },
    "52s": {
      "fold": 0.9444,
      "call": 0.0556
    },
    "62s": {
      "fold": 0.5269,
      "call": 0.4731
    },
    "72s": {
      "fold": 0.6295,
      "call": 0.3705
    },
    "82s": {
      "fold": 0.0646,
      "call": 0.9354
    },
    "92s": {
      "fold": 0.0844,
      "call": 0.9156
    },
    "T2s": {
      "fold": 0.0824,
      "call": 0.9176
    },
    "J2s": {
      "fold": 0.0616,
      "call": 0.9384
    },
    "Q2s": {
      "fold": 0.2294,
      "call": 0.7706
    },
    "K2s": {
      "fold": 0.2365,
      "call": 0.7635
    },
    "A2s": {
      "fold": 0.0,
      "call": 1.0
    },
    "32o": {
      "fold": 0.9275,
      "call": 0.0725
    },
    "33": {
      "fold": 0.3358,
      "call": 0.6642
    },
    "43s": {
      "fold": 0.567,
      "call": 0.433
    },
    "53s": {
      "fold": 0.241,
      "call": 0.759
    },
    "63s": {
      "fold": 0.1863,
      "call": 0.8137
    },
    "73s": {
      "fold": 0.0589,
      "call": 0.9411
    },
    "83s": {
      "fold": 0.0442,
      "call": 0.9558
    },
    "93s": {
      "fold": 0.1289,
      "call": 0.8711
    },
    "T3s": {
      "fold": 0.181,
      "call": 0.819
    },
    "J3s": {
      "fold": 0.2456,
      "call": 0.7544
    },
    "Q3s": {
      "fold": 0.1217,
      "call": 0.8783
    },
    "K3s": {
      "fold": 0.1236,
      "call": 0.8764
    },
    "A3s": {
      "fold": 0.0248,
      "call": 0.9752
    },
    "42o": {
      "fold": 0.8045,
      "call": 0.1955
    },
    "43o": {
      "fold": 0.6125,
      "call": 0.3875
    },
    "44": {
      "fold": 0.2291,
      "call": 0.7709
    },
    "54s": {
      "fold": 0.1929,
      "call": 0.8071
    },
    "64s": {
      "fold": 0.0507,
      "call": 0.9493
    },
    "74s": {
      "fold": 0.2029,
      "call": 0.7971
    },
    "84s": {
      "fold": 0.1648,
      "call": 0.8352
    },
    "94s": {
      "fold": 0.1683,
      "call": 0.8317
    },
    "T4s": {
      "fold": 0.0275,
      "call": 0.9725
    },
    "J4s": {
      "fold": 0.0932,
      "call": 0.9068
    },
    "Q4s": {
      "fold": 0.163,
      "call": 0.837
    },
    "K4s": {
      "fold": 0.0619,
      "call": 0.9381
    },
    "A4s": {
      "fold": 0.0436,
      "call": 0.9564
    },
    "52o": {
      "fold": 0.9434,
      "call": 0.0566
    },
    "53o": {
      "fold": 0.3373,
      "call": 0.6627
    },
    "54o": {
      "fold": 0.2234,
      "call": 0.7766
    },
    "55": {
      "fold": 0.0192,
      "call": 0.9808
    },
    "65s": {
      "fold": 0.0294,
      "call": 0.9706
    },
    "75s": {
      "fold": 0.0426,
      "call": 0.9574
    },
    "85s": {
      "fold": 0.0316,
      "call": 0.9684
    },
    "95s": {
      "fold": 0.0889,
      "call": 0.9111
    },
    "T5s": {
      "fold": 0.0386,
      "call": 0.9614
    },
    "J5s": {
      "fold": 0.0611,
      "call": 0.9389
    },
    "Q5s": {
      "fold": 0.0356,
      "call": 0.9644
    },
    "K5s": {
      "fold": 0.0325,
      "call": 0.9675
    },
    "A5s": {
      "fold": 0.0091,
      "call": 0.9909
    },
    "62o": {
      "fold": 0.9521,
      "call": 0.0479
    },
    "63o": {
      "fold": 0.433,
      "call": 0.567
    },
    "64o": {
      "fold": 0.0369,
      "call": 0.9631
    },
    "65o": {
      "fold": 0.0355,
      "call": 0.9645
    },
    "66": {
      "fold": 0.0403,
      "call": 0.9597
    },
    "76s": {
      "fold": 0.0205,
      "call": 0.9795
    },
    "86s": {
      "fold": 0.0181,
      "call": 0.9819
    },
    "96s": {
      "fold": 0.069,
      "call": 0.931
    },
    "T6s": {
      "fold": 0.012,
      "call": 0.988
    },
    "J6s": {
      "fold": 0.0072,
      "call": 0.9928
    },
    "Q6s": {
      "fold": 0.0245,
      "call": 0.9755
    },
    "K6s": {
      "fold": 0.0231,
      "call": 0.9769
    },
    "A6s": {
      "fold": 0.0032,
      "call": 0.9968
    },
    "72o": {
      "fold": 0.7692,
      "call": 0.2308
    },
    "73o": {
      "fold": 0.0593,
      "call": 0.9407
    },
    "74o": {
      "fold": 0.0787,
      "call": 0.9213
    },
    "75o": {
      "fold": 0.0268,
      "call": 0.9732
    },
    "76o": {
      "fold": 0.0124,
      "call": 0.9876
    },
    "77": {
      "fold": 0.0048,
      "call": 0.9952
    },
    "87s": {
      "fold": 0.0075,
      "call": 0.9925
    },
    "97s": {
      "fold": 0.0,
      "call": 1.0
    },
    "T7s": {
      "fold": 0.0204,
      "call": 0.9796
    },
    "J7s": {
      "fold": 0.0036,
      "call": 0.9964
    },
    "Q7s": {
      "fold": 0.0109,
      "call": 0.9891
    },
    "K7s": {
      "fold": 0.0055,
      "call": 0.9945
    },
    "A7s": {
      "fold": 0.0,
      "call": 1.0
    },
    "82o": {
      "fold": 0.6989,
      "call": 0.3011
    },
    "83o": {
      "fold": 0.2627,
      "call": 0.7373
    },
    "84o": {
      "fold": 0.0376,
      "call": 0.9624
    },
    "85o": {
      "fold": 0.0192,
      "call": 0.9808
    },
    "86o": {
      "fold": 0.0146,
      "call": 0.9854
    },
    "87o": {
      "fold": 0.0069,
      "call": 0.9931
    },
    "88": {
      "fold": 0.0017,
      "call": 0.9983
    },
    "98s": {
      "fold": 0.0082,
      "call": 0.9918
    },
    "T8s": {
      "fold": 0.0067,
      "call": 0.9933
    },
    "J8s": {
      "fold": 0.0024,
      "call": 0.9976
    },
    "Q8s": {
      "fold": 0.0032,
      "call": 0.9968
    },
    "K8s": {
      "fold": 0.0015,
      "call": 0.9985
    },
    "A8s": {
      "fold": 0.0047,
      "call": 0.9953
    },
    "92o": {
      "fold": 0.55,
      "call": 0.45
    },
    "93o": {
      "fold": 0.0598,
      "call": 0.9402
    },
    "94o": {
      "fold": 0.0188,
      "call": 0.9812
    },
    "95o": {
      "fold": 0.0627,
      "call": 0.9373
    },
    "96o": {
      "fold": 0.0088,
      "call": 0.9912
    },
    "97o": {
      "fold": 0.0049,
      "call": 0.9951
    },
    "98o": {
      "fold": 0.0105,
      "call": 0.9895
    },
    "99": {
      "fold": 0.0008,
      "call": 0.9992
    },
    "T9s": {
      "fold": 0.0034,
      "call": 0.9966
    },
    "J9s": {
      "fold": 0.0024,
      "call": 0.9976
    },
    "Q9s": {
      "fold": 0.0012,
      "call": 0.9988
    },
    "K9s": {
      "fold": 0.004,
      "call": 0.996
    },
    "A9s": {
      "fold": 0.0016,
      "call": 0.9984
    },
    "T2o": {
      "fold": 0.5548,
      "call": 0.4452
    },
    "T3o": {
      "fold": 0.1168,
      "call": 0.8832
    },
    "T4o": {
      "fold": 0.0305,
      "call": 0.9695
    },
    "T5o": {
      "fold": 0.0588,
      "call": 0.9412
    },
    "T6o": {
      "fold": 0.0089,
      "call": 0.9911
    },
    "T7o": {
      "fold": 0.0035,
      "call": 0.9965
    },
    "T8o": {
      "fold": 0.0017,
      "call": 0.9983
    },
    "T9o": {
      "fold": 0.0005,
      "call": 0.9995
    },
    "TT": {
      "fold": 0.0007,
      "call": 0.9993
    },
    "JTs": {
      "fold": 0.0042,
      "call": 0.9958
    },
    "QTs": {
      "fold": 0.001,
      "call": 0.999
    },
    "KTs": {
      "fold": 0.0026,
      "call": 0.9974
    },
    "ATs": {
      "fold": 0.0013,
      "call": 0.9987
    },
    "J2o": {
      "fold": 0.1426,
      "call": 0.8574
    },
    "J3o": {
      "fold": 0.1324,
      "call": 0.8676
    },
    "J4o": {
      "fold": 0.0238,
      "call": 0.9762
    },
    "J5o": {
      "fold": 0.0112,
      "call": 0.9888
    },
    "J6o": {
      "fold": 0.0054,
      "call": 0.9946
    },
    "J7o": {
      "fold": 0.0026,
      "call": 0.9974
    },
    "J8o": {
      "fold": 0.0007,
      "call": 0.9993
    },
    "J9o": {
      "fold": 0.0014,
      "call": 0.9986
    },
    "JTo": {
      "fold": 0.0013,
      "call": 0.9987
    },
    "JJ": {
      "fold": 0.0009,
      "call": 0.9991
    },
    "QJs": {
      "fold": 0.0032,
      "call": 0.9968
    },
    "KJs": {
      "fold": 0.0016,
      "call": 0.9984
    },
    "AJs": {
      "fold": 0.0011,
      "call": 0.9989
    },
    "Q2o": {
      "fold": 0.0484,
      "call": 0.9516
    },
    "Q3o": {
      "fold": 0.016,
      "call": 0.984
    },
    "Q4o": {
      "fold": 0.0138,
      "call": 0.9862
    },
    "Q5o": {
      "fold": 0.0089,
      "call": 0.9911
    },
    "Q6o": {
      "fold": 0.005,
      "call": 0.995
    },
    "Q7o": {
      "fold": 0.0084,
      "call": 0.9916
    },
    "Q8o": {
      "fold": 0.0006,
      "call": 0.9994
    },
    "Q9o": {
      "fold": 0.0004,
      "call": 0.9996
    },
    "QTo": {
      "fold": 0.0012,
      "call": 0.9988
    },
    "QJo": {
      "fold": 0.0004,
      "call": 0.9996
    },
    "QQ": {
      "fold": 0.0034,
      "call": 0.9966
    },
    "KQs": {
      "fold": 0.0012,
      "call": 0.9988
    },
    "AQs": {
      "fold": 0.0019,
      "call": 0.9981
    },
    "K2o": {
      "fold": 0.0663,
      "call": 0.9337
    },
    "K3o": {
      "fold": 0.0424,
      "call": 0.9576
    },
    "K4o": {
      "fold": 0.0459,
      "call": 0.9541
    },
    "K5o": {
      "fold": 0.0025,
      "call": 0.9975
    },
    "K6o": {
      "fold": 0.016,
      "call": 0.984
    },
    "K7o": {
      "fold": 0.0043,
      "call": 0.9957
    },
    "K8o": {
      "fold": 0.0014,
      "call": 0.9986
    },
    "K9o": {
      "fold": 0.0012,
      "call": 0.9988
    },
    "KTo": {
      "fold": 0.0004,
      "call": 0.9996
    },
    "KJo": {
      "fold": 0.0004,
      "call": 0.9996
    },
    "KQo": {
      "fold": 0.0004,
      "call": 0.9996
    },
    "KK": {
      "fold": 0.0,
      "call": 1.0
    },
    "AKs": {
      "fold": 0.0013,
      "call": 0.9987
    },
    "A2o": {
      "fold": 0.0626,
      "call": 0.9374
    },
    "A3o": {
      "fold": 0.0131,
      "call": 0.9869
    },
    "A4o": {
      "fold": 0.0482,
      "call": 0.9518
    },
    "A5o": {
      "fold": 0.0277,
      "call": 0.9723
    },
    "A6o": {
      "fold": 0.0026,
      "call": 0.9974
    },
    "A7o": {
      "fold": 0.0008,
      "call": 0.9992
    },
    "A8o": {
      "fold": 0.0004,
      "call": 0.9996
    },
    "A9o": {
      "fold": 0.0004,
      "call": 0.9996
    },
    "ATo": {
      "fold": 0.0012,
      "call": 0.9988
    },
    "AJo": {
      "fold": 0.0004,
      "call": 0.9996
    },
    "AQo": {
      "fold": 0.0014,
      "call": 0.9986
    },
    "AKo": {
      "fold": 0.0011,
      "call": 0.9989
    },
    "AA": {
      "fold": 0.0021,
      "call": 0.9979
    }
  }
}